image_mcp/__init__.py
image_mcp/api_client.py
image_mcp/cli.py
image_mcp/config.py
image_mcp/image_handler.py
image_mcp/server.py
image_mcp/tools.py
termivls-1.0.5.dist-info/METADATA
termivls-1.0.5.dist-info/WHEEL
termivls-1.0.5.dist-info/entry_points.txt
termivls-1.0.5.dist-info/RECORD
