Metadata-Version: 2.4
Name: termivls
Version: 1.0.5
Summary: TermiVis: Visual intelligence for your terminal - MCP server for image analysis
Project-URL: Homepage, https://github.com/zhangbeibei/image-mcp-server
Project-URL: Bug Reports, https://github.com/zhangbeibei/image-mcp-server/issues
Project-URL: Source, https://github.com/zhangbeibei/image-mcp-server
Author-email: TermiVis Team <info@termivls.com>
License: MIT
Keywords: ai,claude-code,image-analysis,mcp,terminal,visual-intelligence
Classifier: Development Status :: 4 - Beta
Classifier: Intended Audience :: Developers
Classifier: License :: OSI Approved :: MIT License
Classifier: Programming Language :: Python :: 3
Classifier: Programming Language :: Python :: 3.10
Classifier: Programming Language :: Python :: 3.11
Classifier: Programming Language :: Python :: 3.12
Classifier: Topic :: Multimedia :: Graphics
Classifier: Topic :: Scientific/Engineering :: Image Processing
Classifier: Topic :: Software Development :: Libraries :: Python Modules
Requires-Python: >=3.10
Requires-Dist: fastapi>=0.110.0
Requires-Dist: httpx[http2]>=0.27.0
Requires-Dist: mcp>=1.0.0
Requires-Dist: pillow>=10.0.0
Requires-Dist: pydantic-settings>=2.2.0
Requires-Dist: pydantic>=2.7.0
Requires-Dist: pytest-asyncio>=0.21.0
Requires-Dist: pytest>=7.0.0
Requires-Dist: python-dotenv>=1.0.0
Requires-Dist: tenacity>=8.2.0
Requires-Dist: typer>=0.9.0
Requires-Dist: uvicorn[standard]>=0.29.0
Provides-Extra: dev
Requires-Dist: mypy>=1.0.0; extra == 'dev'
Requires-Dist: pytest-asyncio>=0.21.0; extra == 'dev'
Requires-Dist: pytest>=7.0.0; extra == 'dev'
Requires-Dist: ruff>=0.1.0; extra == 'dev'
